{
  "schema": "horyzont.public-value-circuit/v0.1",
  "probe_id": "P-0007",
  "distribution": {
    "channel": "public_github_action_subdirectory",
    "path": "p0007",
    "state": "verified_immutable_public_readback",
    "package_commit": "458af9cb64fb2b550d1da1dc7597c935c48ed0de",
    "discovery_commit": "5ab2a72e87b9dca3ba963a8f4b2ca3d17eb13bf8",
    "readback_files": 6
  },
  "external_use": {
    "gate": "successful workflow in a non-owner repository pinned to the immutable package commit and bound to provenance-bearing input plus the emitted result hash",
    "verified": false
  },
  "outcome": {
    "gate": "independent attestation compares the frozen policy with observed outcomes without converting a counterfactual estimate into avoided-loss fact",
    "verified": false
  },
  "capture": {
    "rail": "resilience analysis contract; no automated emergency action or payout authority",
    "amount": 0,
    "verified": false
  },
  "return": {
    "amount": 0,
    "verified": false
  }
}
